rmocd-1.0.0.dist-info/METADATA
rmocd-1.0.0.dist-info/WHEEL
rmocd-1.0.0.dist-info/licenses/LICENSE
rmocd/__init__.py
rmocd/rmocd.cp39-win_amd64.pyd
rmocd-1.0.0.dist-info/RECORD
