Metadata-Version: 2.4
Name: rmocd
Version: 1.0.0
Classifier: License :: OSI Approved :: GNU General Public License v3 or later (GPLv3+)
Classifier: Natural Language :: Portuguese (Brazilian)
Classifier: Programming Language :: Python
Classifier: Programming Language :: Rust
Classifier: Development Status :: 4 - Beta
Classifier: Intended Audience :: Developers
Classifier: Topic :: Software Development :: Libraries
Classifier: Programming Language :: Python :: 3
Classifier: Programming Language :: Python :: 3.12
License-File: LICENSE
Summary: Rapid multi-objective community detection with parallel computation and caching to efficiently handle large-scale graphs.
Keywords: rust,python,community detection,multi-objective optimization,graph analysis
Author: Guilherme Santos
Author-email: Guilherme Santos <gs.oliveira.dev@gmail.com>
License: GPL-3.0-or-later
Project-URL: Repository, https://github.com/0l1ve1r4/rmocd
Project-URL: Issues, https://github.com/0l1ve1r4/rmocd/issues
